{
  "tasks": {
    "5909738679:AAFy6XTZDQLCgW5Av2J29xYQ-HJ0KlYw-10": {
      "server": "https://zayavki.konex.com.ua/telegram",
      "name": "meters_konex_bot",
      "state": true,
      "jobsConfig": [
        {
          "schedule": "0/5 * * ? * *",
          "jobName": "notifyUserToSubmitIndicators",
          "loopExecute": false,
          "request": {
            "method": "POST",
            "serverURL": "https://zayavki.konex.com.ua/telegramUpdates",
            "json": {
              "action": "userNotify"
            }
          }
        },
        {
          "schedule": "0/2 * * ? * *",
          "jobName": "notifyManagerOfNoNSpecifiedIndicators",
          "jobState": true,
          "loopExecute": true,
          "request": {
            "method": "POST",
            "serverURL": "https://zayavki.konex.com.ua/telegramUpdates",
            "json": {
              "chatId": [
                "971483502"
              ],
              "action": "managerNotify"
            }
          }
        }
      ]
    },
    "6034973591:AAH5qoOJ1TEfzi7m2iPXw3A_K8auh6FiNZM": {
      "server": "https://test.vntu.edu.ua/",
      "name": "tester_meters_bot",
      "state": false,
      "jobsConfig": [
        {
          "schedule": "0/2 * * * * ?",
          "jobName": "managerCountersVNTU",
          "loopExecute": true,
          "request": {
            "method": "POST",
            "serverURL": "https://www.bestchange.com/VNTU",
            "headers": {
              "login": "1234",
              "pass": "12334"
            },
            "json": {
              "chatId": [
                "971483502"
              ],
              "action": "managerCounters"
            }
          }
        }
      ]
    }
  }
}